rafa_puc_ia_csv_converter/__init__.py
rafa_puc_ia_csv_converter/converter.py
rafa_puc_ia_csv_converter-0.1.0.dist-info/entry_points.txt
rafa_puc_ia_csv_converter-0.1.0.dist-info/WHEEL
rafa_puc_ia_csv_converter-0.1.0.dist-info/METADATA
rafa_puc_ia_csv_converter-0.1.0.dist-info/RECORD
