Metadata-Version: 2.1
Name: rafa-puc-ia-csv-converter
Version: 0.1.0
Summary: Convert csv to Json. For learning purposes.
Author: Rafael Henrique
Author-email: cerbellus@gmsil.com
Requires-Python: >=3.8,<4.0
Classifier: Programming Language :: Python :: 3
Classifier: Programming Language :: Python :: 3.10
Classifier: Programming Language :: Python :: 3.8
Classifier: Programming Language :: Python :: 3.9
Requires-Dist: click (>=8.0.3,<9.0.0)
Requires-Dist: pandas (>=1.3.4,<2.0.0)
